{
  "kept": [
    {
      "i": 1,
      "timestamp": "04:45",
      "speaker": "Mark Pincus",
      "trimmed": false,
      "tsWas": "04:43",
      "spkWas": "Mark Pincus"
    },
    {
      "i": 2,
      "timestamp": "16:18",
      "speaker": "Mark Pincus",
      "trimmed": false,
      "tsWas": "16:13",
      "spkWas": "Mark Pincus"
    },
    {
      "i": 3,
      "timestamp": "24:28",
      "speaker": "Mark Pincus",
      "trimmed": false,
      "tsWas": "24:16",
      "spkWas": "Mark Pincus"
    },
    {
      "i": 4,
      "timestamp": "27:20",
      "speaker": "Mark Pincus",
      "trimmed": true,
      "tsWas": "27:20",
      "spkWas": "Mark Pincus"
    },
    {
      "i": 5,
      "timestamp": "33:38",
      "speaker": "Mark Pincus",
      "trimmed": false,
      "tsWas": "33:38",
      "spkWas": "Mark Pincus"
    },
    {
      "i": 7,
      "timestamp": "34:32",
      "speaker": "Mark Pincus",
      "trimmed": false,
      "tsWas": "34:32",
      "spkWas": "Mark Pincus"
    },
    {
      "i": 8,
      "timestamp": "36:27",
      "speaker": "Mark Pincus",
      "trimmed": true,
      "tsWas": "36:27",
      "spkWas": "Mark Pincus"
    },
    {
      "i": 9,
      "timestamp": "27:03",
      "speaker": "Mark Pincus",
      "trimmed": false,
      "tsWas": "27:03",
      "spkWas": "Mark Pincus"
    },
    {
      "i": 10,
      "timestamp": "58:09",
      "speaker": "Mark Pincus",
      "trimmed": false,
      "tsWas": "58:09",
      "spkWas": "Mark Pincus"
    },
    {
      "i": 11,
      "timestamp": "79:49",
      "speaker": "Mark Pincus",
      "trimmed": false,
      "tsWas": "79:49",
      "spkWas": "Mark Pincus"
    },
    {
      "i": 12,
      "timestamp": "85:43",
      "speaker": "Mark Pincus",
      "trimmed": false,
      "tsWas": "85:43",
      "spkWas": "Mark Pincus"
    }
  ],
  "dropped": [
    {
      "i": 6,
      "reason": "逐字命中不了(裁剪后仍无)",
      "en": "Hope is confidence without basis."
    }
  ]
}